setup.py
bf3stats/__init__.py
bf3stats/api.py
bf3stats/utils.py
bf3stats.egg-info/PKG-INFO
bf3stats.egg-info/SOURCES.txt
bf3stats.egg-info/dependency_links.txt
bf3stats.egg-info/top_level.txt