Metadata-Version: 1.0
Name: bf3stats
Version: 0.99
Summary: Python interface to the bf3stats.com API
Home-page: https://github.com/ozon/python-bf3stats
Author: Harry Gabriel
Author-email: h.gabriel@nodefab.de
License: GPLv2
Keywords: bf3stats library
Platform: UNKNOWN
